aiida_grouppathx/__init__.py
aiida_grouppathx/cli.py
aiida_grouppathx/launch_manager.py
aiida_grouppathx/pathx.py
aiida_grouppathx-0.2.6.dist-info/entry_points.txt
aiida_grouppathx-0.2.6.dist-info/licenses/LICENSE
aiida_grouppathx-0.2.6.dist-info/WHEEL
aiida_grouppathx-0.2.6.dist-info/METADATA
aiida_grouppathx-0.2.6.dist-info/RECORD
